konfai/__init__.py
konfai/app.py
konfai/app_server.py
konfai/evaluator.py
konfai/main.py
konfai/predictor.py
konfai/trainer.py
konfai/data/__init__.py
konfai/data/augmentation.py
konfai/data/data_manager.py
konfai/data/patching.py
konfai/data/transform.py
konfai/metric/__init__.py
konfai/metric/measure.py
konfai/metric/schedulers.py
konfai/models/classification/convNeXt.py
konfai/models/classification/resnet.py
konfai/models/generation/cStyleGan.py
konfai/models/generation/ddpm.py
konfai/models/generation/diffusionGan.py
konfai/models/generation/gan.py
konfai/models/generation/vae.py
konfai/models/registration/registration.py
konfai/models/representation/representation.py
konfai/models/segmentation/NestedUNet.py
konfai/models/segmentation/UNet.py
konfai/network/__init__.py
konfai/network/blocks.py
konfai/network/network.py
konfai/utils/ITK.py
konfai/utils/__init__.py
konfai/utils/config.py
konfai/utils/dataset.py
konfai/utils/utils.py
konfai-1.5.2.dist-info/licenses/LICENSE
konfai-1.5.2.dist-info/METADATA
konfai-1.5.2.dist-info/WHEEL
konfai-1.5.2.dist-info/entry_points.txt
konfai-1.5.2.dist-info/top_level.txt
konfai-1.5.2.dist-info/RECORD
