Metadata-Version: 2.4
Name: konfai
Version: 1.5.2
Summary: A Modular and configurable Deep Learning framework with YAML and PyTorch
Author-email: Valentin Boussot <boussot.v@gmail.com>
License:                                  Apache License
Project-URL: Homepage, https://github.com/vboussot/KonfAI
Project-URL: Repository, https://github.com/vboussot/KonfAI
Project-URL: Issues, https://github.com/vboussot/KonfAI/issues
Project-URL: License, https://www.apache.org/licenses/LICENSE-2.0
Requires-Python: >=3.10
License-File: LICENSE
Requires-Dist: torch
Requires-Dist: tqdm
Requires-Dist: numpy
Requires-Dist: ruamel.yaml
Requires-Dist: psutil
Requires-Dist: tensorboard
Requires-Dist: SimpleITK
Requires-Dist: lxml
Requires-Dist: h5py
Requires-Dist: nvidia-ml-py
Requires-Dist: requests
Requires-Dist: huggingface_hub
Provides-Extra: vtk
Requires-Dist: vtk; extra == "vtk"
Provides-Extra: lpips
Requires-Dist: lpips; extra == "lpips"
Provides-Extra: cluster
Requires-Dist: submitit; extra == "cluster"
Provides-Extra: server
Requires-Dist: fastapi; extra == "server"
Requires-Dist: uvicorn; extra == "server"
Requires-Dist: python-multipart; extra == "server"
Dynamic: license-file
